pysyntect-0.3.0.dist-info/METADATA
pysyntect-0.3.0.dist-info/WHEEL
syntect/grammars/1c-query.sublime-syntax
syntect/grammars/1c.sublime-syntax
syntect/grammars/ABAP.sublime-syntax
syntect/grammars/ABL.sublime-syntax
syntect/grammars/abnf.sublime-syntax
syntect/grammars/ActionScript 3.sublime-syntax
syntect/grammars/ACUCOBOL.sublime-syntax
syntect/grammars/Ada.sublime-syntax
syntect/grammars/afm.sublime-syntax
syntect/grammars/agc.sublime-syntax
syntect/grammars/Agda.sublime-syntax
syntect/grammars/alloy.sublime-syntax
syntect/grammars/AMPL.sublime-syntax
syntect/grammars/AngelScript.sublime-syntax
syntect/grammars/Ant.sublime-syntax
syntect/grammars/ANTLR.sublime-syntax
syntect/grammars/Apache.sublime-syntax
syntect/grammars/APIBlueprint.sublime-syntax
syntect/grammars/apl.sublime-syntax
syntect/grammars/AppleScript.sublime-syntax
syntect/grammars/AsciiDoc.sublime-syntax
syntect/grammars/AsDoc.sublime-syntax
syntect/grammars/asn1.sublime-syntax
syntect/grammars/ASP.sublime-syntax
syntect/grammars/AspectJ.sublime-syntax
syntect/grammars/Assembly (x86).sublime-syntax
syntect/grammars/Assembly x86 AT&T.sublime-syntax
syntect/grammars/Assembly x86.sublime-syntax
syntect/grammars/ats.sublime-syntax
syntect/grammars/AutoHotkey.sublime-syntax
syntect/grammars/AutoIt.sublime-syntax
syntect/grammars/AWK.sublime-syntax
syntect/grammars/ballerina.sublime-syntax
syntect/grammars/batchfile.sublime-syntax
syntect/grammars/bdf.sublime-syntax
syntect/grammars/Befunge-93.sublime-syntax
syntect/grammars/Bibtex.sublime-syntax
syntect/grammars/Bind Zone Files.sublime-syntax
syntect/grammars/blade.sublime-syntax
syntect/grammars/BlitzMax.sublime-syntax
syntect/grammars/bnf.sublime-syntax
syntect/grammars/Boo.sublime-syntax
syntect/grammars/Brainfuck.sublime-syntax
syntect/grammars/BrightAuthor Project File.sublime-syntax
syntect/grammars/BrightScript.sublime-syntax
syntect/grammars/BSV.sublime-syntax
syntect/grammars/C++.sublime-syntax
syntect/grammars/C.sublime-syntax
syntect/grammars/c2hs.sublime-syntax
syntect/grammars/cabal.sublime-syntax
pysyntect-0.3.0.dist-info/RECORD
