Metadata-Version: 2.1
Name: pysyntect
Version: 0.3.0
Summary: Python bindings for the syntect syntax highlighter.
Keywords: syntax highlighting syntect
Author: Edgar Andrés Margffoy Tuay <andfoy@gmail.com>
Author-Email: Edgar Andrés Margffoy Tuay <andfoy@gmail.com>
License: MIT
